contextlib.py
setup.py
micropython_contextlib.egg-info/PKG-INFO
micropython_contextlib.egg-info/SOURCES.txt
micropython_contextlib.egg-info/dependency_links.txt
micropython_contextlib.egg-info/requires.txt
micropython_contextlib.egg-info/top_level.txt